[{"GlobalConfig":[{"id":1,"globalConfig":{"email":"bharathms@gain-insights.com","password":"U2FsdGVkX19x/uKvQPAClnoGW2VIwErzlrBPkQRSjaaoOfLkIyUpDeqvq2GTY7mgLB9gDTNsphe8osimtqXPTg==","username":"MSB301","repository":"CodeManagement","storageUrl":"github.com","storageType":"Github"},"type":"repository","createdAt":"2024-05-15T12:20:15.185Z","updatedAt":"2024-05-15T12:20:15.185Z"}]},{"Jobs":[{"id":"2a8233dc-6d5c-4ebb-8663-0ef7f4e11a66","name":"Job1","repositoryId":1,"repositoryType":"QS","repositoryName":"Combo Chart","projectId":1,"projectName":"Work","destinationServer":1,"destinationApplication":"f5d6a0cf-a739-48d8-96bb-045f473ec5e7","destinationApplicationName":"Combo Chart","jobKey":null,"lastRun":null,"status":"Initial Movement","loaded":null,"initialMovement":false,"streamName":"aaec8d41-5201-43ab-809f-3063750dfafd","createdBy":"1","imagePath":null,"createdAt":"2024-05-15T11:50:59.454Z","updatedAt":"2024-05-16T05:08:32.836Z"}]},{"JobsHistory":[{"id":1,"jobId":"2a8233dc-6d5c-4ebb-8663-0ef7f4e11a66","packageId":1,"executedTime":"1715836109203","executedType":"deployment","type":"package","status":"Success","promotor":"Admin","message":["Job initiated","App updated"],"createdAt":"2024-05-16T05:08:30.176Z","updatedAt":"2024-05-16T05:08:32.840Z"}]},{"Packages":[{"id":1,"name":"Test","jobsList":[{"id":"2a8233dc-6d5c-4ebb-8663-0ef7f4e11a66","name":"Job1","repoId":1,"checked":true}],"executedTime":"1715836109203","createdAt":"2024-05-16T05:08:19.326Z","updatedAt":"2024-05-16T05:08:30.183Z"}]},{"Projects":[{"id":1,"name":"Work","description":"","createdBy":1,"imagePath":null,"assignedUsers":[{"userId":1,"projectRoles":"Admin"}],"createdAt":"2024-05-15T11:49:00.237Z","updatedAt":"2024-05-15T11:49:00.237Z"}]},{"QlikUsers":[{"id":1,"userId":1,"serverId":1,"userName":"bharathms","userDirectory":"GAIN-INSIGHTS","createdAt":"2024-05-15T11:48:15.036Z","updatedAt":"2024-05-15T11:48:15.036Z"}]},{"Repositories":[{"id":1,"name":"Combo Chart","projectId":1,"repositoryType":{"env":"QS","type":"QS"},"serverId":1,"streamName":"Work","streamId":"Work","sourceApplicationId":"13e32438-03cd-47eb-8310-0a501a32daaf","sourceApplicationName":"Combo Chart","description":"","branches":1,"sourceName":"Git","mergeRequests":null,"createdBy":1,"createdAt":"2024-05-15T11:49:00.256Z","updatedAt":"2024-05-15T11:49:01.520Z"},{"id":2,"name":"B1","projectId":1,"repositoryType":{"env":"QS","type":"QS"},"serverId":1,"streamName":"Work","streamId":"Work","sourceApplicationId":"4797f496-991b-4cf4-80fa-a24279a95a68","sourceApplicationName":"B1","description":"","branches":3,"sourceName":"Git","mergeRequests":null,"createdBy":1,"createdAt":"2024-05-16T05:01:15.402Z","updatedAt":"2024-05-16T05:02:29.990Z"},{"id":3,"name":"Consumer Sales","projectId":1,"repositoryType":{"env":"QS","type":"QS"},"serverId":1,"streamName":"Work","streamId":"Work","sourceApplicationId":"985975e8-82b1-458d-b8db-3c20e28a28e2","sourceApplicationName":"Consumer Sales","description":"","branches":1,"sourceName":"Git","mergeRequests":null,"createdBy":1,"createdAt":"2024-05-16T05:14:18.300Z","updatedAt":"2024-05-16T05:14:22.459Z"},{"id":4,"name":"Consumer Sales_New","projectId":1,"repositoryType":{"env":"QS","type":"QS"},"serverId":1,"streamName":"Work","streamId":"Work","sourceApplicationId":"462aa24a-fb5b-448a-aa0c-83647f9ab0da","sourceApplicationName":"Consumer Sales_New","description":"","branches":1,"sourceName":"Git","mergeRequests":null,"createdBy":1,"createdAt":"2024-05-16T05:14:39.202Z","updatedAt":"2024-05-16T05:14:43.067Z"},{"id":5,"name":"Test Calendar","projectId":1,"repositoryType":{"env":"QS","type":"QS"},"serverId":1,"streamName":"Work","streamId":"Work","sourceApplicationId":"284094f5-194e-4dc0-b29f-43914f219565","sourceApplicationName":"Test Calendar","description":"","branches":1,"sourceName":"Git","mergeRequests":null,"createdBy":1,"createdAt":"2024-05-16T05:14:58.566Z","updatedAt":"2024-05-16T05:14:59.913Z"},{"id":6,"name":"GTM - Straight Table(1)","projectId":1,"repositoryType":{"env":"QS","type":"QS"},"serverId":1,"streamName":"Work","streamId":"Work","sourceApplicationId":"4324a10e-73ab-4271-adba-ab26fa7c0873","sourceApplicationName":"GTM - Straight Table(1)","description":"","branches":1,"sourceName":"Git","mergeRequests":null,"createdBy":1,"createdAt":"2024-05-16T05:15:15.900Z","updatedAt":"2024-05-16T05:15:17.433Z"},{"id":7,"name":"qlikAccess (3)_First_Empty","projectId":1,"repositoryType":{"env":"QS","type":"QS"},"serverId":1,"streamName":"Work","streamId":"Work","sourceApplicationId":"fb972c03-6e01-4f59-9133-fefa5e99c3fa","sourceApplicationName":"qlikAccess (3)_First_Empty","description":"","branches":1,"sourceName":"Git","mergeRequests":null,"createdBy":1,"createdAt":"2024-05-16T05:15:44.049Z","updatedAt":"2024-05-16T05:15:45.341Z"},{"id":8,"name":"After App change","projectId":1,"repositoryType":{"env":"QS","type":"QS"},"serverId":1,"streamName":"Work","streamId":"Work","sourceApplicationId":"0cd4e1a4-f5ab-4677-8e49-1b7a23183e6e","sourceApplicationName":"After App change","description":"","branches":1,"sourceName":"Git","mergeRequests":null,"createdBy":1,"createdAt":"2024-05-16T05:16:07.363Z","updatedAt":"2024-05-16T05:16:09.473Z"}]},{"Roles":[{"id":1,"name":"SuperUser","createdAt":"2024-05-15T11:46:28.558Z","updatedAt":"2024-05-15T11:46:28.558Z"},{"id":2,"name":"Manager","createdAt":"2024-05-15T11:46:28.559Z","updatedAt":"2024-05-15T11:46:28.559Z"},{"id":3,"name":"Developer","createdAt":"2024-05-15T11:46:28.559Z","updatedAt":"2024-05-15T11:46:28.559Z"},{"id":4,"name":"Promoter","createdAt":"2024-05-15T11:46:28.559Z","updatedAt":"2024-05-15T11:46:28.559Z"}]},{"Servers":[{"id":1,"type":"QS","name":"Local","hubUrl":"https://j1bvds3.gain-insights.in","host":"j1bvds3.gain-insights.in","port":"","virtualProxy":null,"isSecure":true,"defaultUser":"bharathms","defaultDirectory":"GAIN-INSIGHTS","authToken":null,"createdBy":1,"createdAt":"2024-05-15T11:48:15.025Z"}]},{"Settings":[]},{"Users":[{"id":1,"name":"Admin","activeDirectory":null,"email":"admin@senseops.com","password":"U2FsdGVkX1+pja+u634AHI6Q1dMrR0TIRfIsIwr/cS0=","roleId":1,"resetKey":null,"refreshTokens":["eyJhbGciOiJIUzI1NiIsInR5cCI6IkpXVCJ9.eyJ1SWQiOjEsImlhdCI6MTcxNTgzNTQ4MywiZXhwIjoxNzE1ODcxNDgzfQ.vjqmhFsUuyRzw4MNLF92nYFtsmufvieXPH_Dm_WnoVA"],"createdAt":"2024-05-15T11:46:28.559Z","updatedAt":"2024-05-15T11:46:28.559Z"}]}]